{
  "key": "plugin_content_manager_configuration_content_types::api::project-compensator.project-compensator",
  "value": {
    "settings": {
      "bulkable": true,
      "filterable": true,
      "searchable": true,
      "pageSize": 10,
      "mainField": "id",
      "defaultSortBy": "id",
      "defaultSortOrder": "ASC"
    },
    "metadatas": {
      "id": {
        "edit": {},
        "list": {
          "label": "id",
          "searchable": true,
          "sortable": true
        }
      },
      "amountFunded": {
        "edit": {
          "label": "amountFunded",
          "description": "",
          "placeholder": "",
          "visible": true,
          "editable": true
        },
        "list": {
          "label": "amountFunded",
          "searchable": true,
          "sortable": true
        }
      },
      "compensator": {
        "edit": {
          "label": "compensator",
          "description": "",
          "placeholder": "",
          "visible": true,
          "editable": true,
          "mainField": "name"
        },
        "list": {
          "label": "compensator",
          "searchable": true,
          "sortable": true
        }
      },
      "project": {
        "edit": {
          "label": "project",
          "description": "",
          "placeholder": "",
          "visible": true,
          "editable": true,
          "mainField": "name"
        },
        "list": {
          "label": "project",
          "searchable": true,
          "sortable": true
        }
      },
      "capsFunded": {
        "edit": {
          "label": "capsFunded",
          "description": "",
          "placeholder": "",
          "visible": true,
          "editable": true
        },
        "list": {
          "label": "capsFunded",
          "searchable": true,
          "sortable": true
        }
      },
      "createdAt": {
        "edit": {
          "label": "createdAt",
          "description": "",
          "placeholder": "",
          "visible": false,
          "editable": true
        },
        "list": {
          "label": "createdAt",
          "searchable": true,
          "sortable": true
        }
      },
      "updatedAt": {
        "edit": {
          "label": "updatedAt",
          "description": "",
          "placeholder": "",
          "visible": false,
          "editable": true
        },
        "list": {
          "label": "updatedAt",
          "searchable": true,
          "sortable": true
        }
      },
      "createdBy": {
        "edit": {
          "label": "createdBy",
          "description": "",
          "placeholder": "",
          "visible": false,
          "editable": true,
          "mainField": "firstname"
        },
        "list": {
          "label": "createdBy",
          "searchable": true,
          "sortable": true
        }
      },
      "updatedBy": {
        "edit": {
          "label": "updatedBy",
          "description": "",
          "placeholder": "",
          "visible": false,
          "editable": true,
          "mainField": "firstname"
        },
        "list": {
          "label": "updatedBy",
          "searchable": true,
          "sortable": true
        }
      }
    },
    "layouts": {
      "list": [
        "id",
        "amountFunded",
        "compensator"
      ],
      "edit": [
        [
          {
            "name": "amountFunded",
            "size": 4
          }
        ],
        [
          {
            "name": "compensator",
            "size": 6
          },
          {
            "name": "project",
            "size": 6
          }
        ],
        [
          {
            "name": "capsFunded",
            "size": 4
          }
        ]
      ]
    },
    "uid": "api::project-compensator.project-compensator"
  },
  "type": "object",
  "environment": null,
  "tag": null
}